{
"page11": ["gallery/page11/1.jpg","gallery/page11/2.jpg"],
"page12": ["gallery/page12/1.jpg","gallery/page12/2.jpg"],
"page18": ["gallery/page18/1.jpg","gallery/page18/2.jpg","gallery/page18/3.jpg","gallery/page18/4.jpg","gallery/page18/5.jpg"],
"page23": ["gallery/page23/1.jpg","gallery/page23/2.jpg","gallery/page23/3.jpg","gallery/page23/4.jpg","gallery/page23/5.jpg"],
"page27": ["gallery/page27/1.jpg"],
"page28": ["gallery/page28/1.jpg"],
"page30": ["gallery/page30/1.jpg","gallery/page30/2.jpg"],
"page31": ["gallery/page31/1.jpg"],
"page32": ["gallery/page32/1.jpg"],
"page34": ["gallery/page34/1.jpg","gallery/page34/2.jpg"],
"page35": ["gallery/page35/1.jpg","gallery/page35/2.jpg","gallery/page35/3.jpg","gallery/page35/4.jpg","gallery/page35/5.jpg","gallery/page35/6.jpg","gallery/page35/7.jpg","gallery/page35/8.jpg","gallery/page35/9.jpg","gallery/page35/10.jpg","gallery/page35/11.jpg","gallery/page35/12.jpg","gallery/page35/13.jpg","gallery/page35/14.jpg","gallery/page35/15.jpg","gallery/page35/16.jpg","gallery/page35/17.jpg","gallery/page35/18.jpg","gallery/page35/19.jpg","gallery/page35/20.jpg","gallery/page35/21.jpg","gallery/page35/22.jpg","gallery/page35/23.jpg","gallery/page35/24.jpg","gallery/page35/25.jpg","gallery/page35/26.jpg","gallery/page35/27.jpg","gallery/page35/28.jpg","gallery/page35/29.jpg","gallery/page35/30.jpg","gallery/page35/31.jpg","gallery/page35/32.jpg","gallery/page35/33.jpg","gallery/page35/34.jpg","gallery/page35/35.jpg","gallery/page35/36.jpg","gallery/page35/37.jpg","gallery/page35/38.jpg","gallery/page35/39.jpg","gallery/page35/40.jpg","gallery/page35/41.jpg","gallery/page35/42.jpg","gallery/page35/43.jpg","gallery/page35/44.jpg","gallery/page35/45.jpg","gallery/page35/46.jpg","gallery/page35/47.jpg","gallery/page35/48.jpg","gallery/page35/49.jpg","gallery/page35/50.jpg","gallery/page35/51.jpg","gallery/page35/52.jpg","gallery/page35/53.jpg","gallery/page35/54.jpg","gallery/page35/55.jpg","gallery/page35/56.jpg","gallery/page35/57.jpg","gallery/page35/58.jpg","gallery/page35/59.jpg","gallery/page35/60.jpg","gallery/page35/61.jpg","gallery/page35/62.jpg","gallery/page35/63.jpg","gallery/page35/64.jpg","gallery/page35/65.jpg","gallery/page35/66.jpg","gallery/page35/67.jpg","gallery/page35/68.jpg","gallery/page35/69.jpg","gallery/page35/70.jpg","gallery/page35/71.jpg","gallery/page35/72.jpg","gallery/page35/73.jpg","gallery/page35/74.jpg","gallery/page35/75.jpg","gallery/page35/76.jpg","gallery/page35/77.jpg","gallery/page35/78.jpg","gallery/page35/79.jpg","gallery/page35/80.jpg","gallery/page35/81.jpg","gallery/page35/82.jpg","gallery/page35/83.jpg","gallery/page35/84.jpg","gallery/page35/85.jpg","gallery/page35/86.jpg","gallery/page35/87.jpg","gallery/page35/88.jpg","gallery/page35/89.jpg","gallery/page35/90.jpg","gallery/page35/91.jpg","gallery/page35/92.jpg","gallery/page35/93.jpg","gallery/page35/94.jpg","gallery/page35/95.jpg","gallery/page35/96.jpg","gallery/page35/97.jpg","gallery/page35/98.jpg","gallery/page35/99.jpg","gallery/page35/100.jpg","gallery/page35/101.jpg","gallery/page35/102.jpg","gallery/page35/103.jpg","gallery/page35/104.jpg","gallery/page35/105.jpg","gallery/page35/106.jpg","gallery/page35/107.jpg","gallery/page35/108.jpg","gallery/page35/109.jpg","gallery/page35/110.jpg","gallery/page35/111.jpg","gallery/page35/112.jpg","gallery/page35/113.jpg","gallery/page35/114.jpg","gallery/page35/115.jpg","gallery/page35/116.jpg","gallery/page35/117.jpg","gallery/page35/118.jpg","gallery/page35/119.jpg","gallery/page35/120.jpg","gallery/page35/121.jpg","gallery/page35/122.jpg","gallery/page35/123.jpg","gallery/page35/124.jpg","gallery/page35/125.jpg","gallery/page35/126.jpg","gallery/page35/127.jpg","gallery/page35/128.jpg","gallery/page35/129.jpg","gallery/page35/130.jpg","gallery/page35/131.jpg","gallery/page35/132.jpg","gallery/page35/133.jpg","gallery/page35/134.jpg","gallery/page35/135.jpg","gallery/page35/136.jpg","gallery/page35/137.jpg","gallery/page35/138.jpg","gallery/page35/139.jpg","gallery/page35/140.jpg","gallery/page35/141.jpg","gallery/page35/142.jpg","gallery/page35/143.jpg","gallery/page35/144.jpg","gallery/page35/145.jpg","gallery/page35/146.jpg","gallery/page35/147.jpg","gallery/page35/148.jpg","gallery/page35/149.jpg","gallery/page35/150.jpg","gallery/page35/151.jpg","gallery/page35/152.jpg","gallery/page35/153.jpg","gallery/page35/154.jpg","gallery/page35/155.jpg","gallery/page35/156.jpg","gallery/page35/157.jpg","gallery/page35/158.jpg","gallery/page35/159.jpg","gallery/page35/160.jpg","gallery/page35/161.jpg","gallery/page35/162.jpg","gallery/page35/163.jpg","gallery/page35/164.jpg","gallery/page35/165.jpg","gallery/page35/166.jpg","gallery/page35/167.jpg","gallery/page35/168.jpg","gallery/page35/169.jpg","gallery/page35/170.jpg","gallery/page35/171.jpg","gallery/page35/172.jpg","gallery/page35/173.jpg","gallery/page35/174.jpg","gallery/page35/175.jpg","gallery/page35/176.jpg"]
}
